{
  "completions": [
    {
      "source": "COURAGE",
      "parentId": 10316,
      "stepIndex": 0,
      "label": "🔥 Book Genevieve's May ticket home 📝",
      "uid": "COURAGE:10316:0",
      "_ts": "2026-06-16T01:05:23.090Z"
    }
  ],
  "adds": [
    {
      "source": "PLUS_ADD",
      "label": "Clean up garage shelf from mice",
      "_addedAt": "2026-06-16T00:29:13.935Z",
      "_ts": "2026-06-16T00:29:14.047Z"
    }
  ],
  "mirroredAt": "2026-06-16T01:05:23.344Z",
  "counts": {
    "completions": 1,
    "adds": 1
  }
}