{
  "completions": [
    {
      "source": "SPIN_WHEEL",
      "row": 48,
      "label": "Refill Taha affair",
      "uid": "SPIN:427",
      "_ts": "2026-07-22T06:07:57.537Z"
    },
    {
      "source": "SPIN_WHEEL",
      "row": 73,
      "label": "Pick someone for pillow",
      "uid": "SPIN:476",
      "_ts": "2026-07-22T06:08:10.350Z"
    },
    {
      "source": "SPIN_WHEEL",
      "row": 70,
      "label": "Weed with Evan :)",
      "uid": "SPIN:473",
      "_ts": "2026-07-22T06:08:30.931Z"
    },
    {
      "source": "ZONES",
      "row": 82,
      "zid": 81,
      "floor": "Personal",
      "label": "👱‍♀️ Face Exfoliation",
      "uid": "ZONES:81",
      "_ts": "2026-07-22T06:09:08.449Z"
    }
  ],
  "adds": [],
  "mirroredAt": "2026-07-22T06:09:08.686Z",
  "counts": {
    "completions": 4,
    "adds": 0
  }
}